{
  "data": [
    {
      "num": "SGB3727192",
      "date": "2022-03-05",
      "weight": 20500,
      "com": "",
      "carNum": ""
    },
    {
      "num": "SGB3727123",
      "date": "2022-02-04",
      "weight": 20400,
      "com": "광양",
      "carNum": "43타1524"
    },
    {
      "num": "SGB3727124",
      "date": "2022-03-08",
      "weight": 10500,
      "com": "",
      "carNum": ""
    },
    {
      "num": "SGB3727225",
      "date": "2022-03-07",
      "weight": 2500,
      "com": "",
      "carNum": ""
    },
    {
      "num": "SGB3727126",
      "date": "2022-03-09",
      "weight": 20800,
      "com": "",
      "carNum": ""
    },
    {
      "num": "SGB3727127",
      "date": "2022-03-03",
      "weight": 22300,
      "com": "",
      "carNum": ""
    },
    {
      "num": "SGB3727120",
      "date": "2022-03-04",
      "weight": 21560,
      "com": "",
      "carNum": ""
    },
    {
      "num": "SGB3727178",
      "date": "2022-03-04",
      "weight": 32100,
      "com": "포항",
      "carNum": "55바1234"
    },
    {
      "num": "SGB3327146",
      "date": "2022-03-04",
      "weight": 17500,
      "com": "",
      "carNum": ""
    },
    {
      "num": "SGB3427165",
      "date": "2022-03-04",
      "weight": 12500,
      "com": "",
      "carNum": ""
    },
    {
      "num": "SGB3123192",
      "date": "2022-03-04",
      "weight": 20500,
      "com": "",
      "carNum": ""
    },
    {
      "num": "SGB3227123",
      "date": "2022-03-04",
      "weight": 20400,
      "com": "",
      "carNum": ""
    },
    {
      "num": "SGB3827124",
      "date": "2022-03-04",
      "weight": 10500,
      "com": "",
      "carNum": ""
    },
    {
      "num": "SGB3927126",
      "date": "2022-03-04",
      "weight": 20800,
      "com": "",
      "carNum": ""
    },
    {
      "num": "SGB3527225",
      "date": "2022-03-04",
      "weight": 32500,
      "com": "",
      "carNum": ""
    },
    {
      "num": "SGB3527127",
      "date": "2022-03-04",
      "weight": 22300,
      "com": "",
      "carNum": ""
    },
    {
      "num": "SGB3127120",
      "date": "2022-03-04",
      "weight": 21560,
      "com": "",
      "carNum": ""
    },
    {
      "num": "SGB3227178",
      "date": "2022-03-04",
      "weight": 32100,
      "com": "",
      "carNum": ""
    },
    {
      "num": "SGB3737165",
      "date": "2022-03-04",
      "weight": 12500,
      "com": "",
      "carNum": ""
    },
    {
      "num": "SGB3427146",
      "date": "2022-03-04",
      "weight": 17500,
      "com": "",
      "carNum": ""
    }
  ]
}

